chainer_watchdog-0.0.1.dist-info/DESCRIPTION.rst
chainer_watchdog-0.0.1.dist-info/METADATA
chainer_watchdog-0.0.1.dist-info/RECORD
chainer_watchdog-0.0.1.dist-info/WHEEL
chainer_watchdog-0.0.1.dist-info/metadata.json
chainer_watchdog-0.0.1.dist-info/top_level.txt
watchdog/__init__.py
watchdog/_version.py
watchdog/actions.py
watchdog/estimators.py
watchdog/extension.py
watchdog/misc.py
