Metadata-Version: 2.0
Name: chainer-watchdog
Version: 0.0.1
Summary: Watchdog extension for Chainer
Home-page: https://github.com/dtaniwaki/chainer-watchdog
Author: Daisuke Taniwaki
Author-email: daisuketaniwaki@gmail.com
License: MIT
Keywords: chainer extension
Platform: UNKNOWN
Classifier: Development Status :: 3 - Alpha
Classifier: License :: OSI Approved :: MIT License
Classifier: Programming Language :: Python :: 2.7
Classifier: Programming Language :: Python :: 3.4
Classifier: Programming Language :: Python :: 3.5
Classifier: Programming Language :: Python :: 3.6
Requires-Dist: chainer (<5dev,>=3.0)
Requires-Dist: six (<1.12dev,>=1.11.0)
Requires-Dist: dateutils (<1dev,>=0.6.6)
Provides-Extra: dev
Requires-Dist: pytest-runner (<3dev,>=2.0); extra == 'dev'
Requires-Dist: tox (<3dev,>=2.7); extra == 'dev'
Requires-Dist: detox (<1dev,>=0.11); extra == 'dev'
Requires-Dist: bumpversion (<1dev,>=0.5.3); extra == 'dev'
Provides-Extra: docs
Requires-Dist: sphinx (<1.8dev,>=1.7.1); extra == 'docs'
Requires-Dist: sphinx-rtd-theme (<0.3dev,>=0.2.4); extra == 'docs'
Requires-Dist: sphinxcontrib-blockdiag (<1.6dev,>=1.5.5); extra == 'docs'
Provides-Extra: lint
Requires-Dist: flake8 (<4dev,>=3.5.0); extra == 'lint'
Requires-Dist: flake8-blind-except (<1dev,>=0.1.1); extra == 'lint'
Requires-Dist: flake8-import-order (<1dev,>=0.16); extra == 'lint'
Requires-Dist: flake8-html (<1dev,>=0.4.0); extra == 'lint'
Requires-Dist: autopep8 (<2dev,>=1.3); extra == 'lint'
Requires-Dist: autoflake (<2dev,>=1.1); extra == 'lint'
Requires-Dist: mypy (<1dev,>=0.580); extra == 'lint'
Provides-Extra: test
Requires-Dist: pytest (<3.3,>=3.0); extra == 'test'
Requires-Dist: pytest-cov (<3dev,>=2.5); extra == 'test'
Requires-Dist: pytest-html (<2dev,>=1.15.2); extra == 'test'
Requires-Dist: pytest-describe (<1dev,>=0.11); extra == 'test'
Requires-Dist: mock (<3dev,>=2.0.0); extra == 'test'
Requires-Dist: slackclient (<2dev,>=1.2.1); extra == 'test'
Requires-Dist: slackweb (<2dev,>=1.0.5); extra == 'test'
